meltano_map_transform/__init__.py
meltano_map_transform/mapper.py
meltano_map_transform-0.12.1.dist-info/METADATA
meltano_map_transform-0.12.1.dist-info/WHEEL
meltano_map_transform-0.12.1.dist-info/entry_points.txt
meltano_map_transform-0.12.1.dist-info/licenses/LICENSE
meltano_map_transform-0.12.1.dist-info/RECORD
