Metadata-Version: 2.4
Name: meltano-map-transform
Version: 0.12.1
Summary: Singer-compatible inline map transformer, built with the Meltano SDK for Singer Taps.
Project-URL: Documentation, https://github.com/MeltanoLabs/meltano-map-transform#readme
Project-URL: Homepage, https://github.com/MeltanoLabs/meltano-map-transform
Project-URL: Repository, https://github.com/MeltanoLabs/meltano-map-transform
Author: Meltano Team and Contributors
License-Expression: Apache-2.0
License-File: LICENSE
Keywords: ELT,Inline Transformation,singer.io
Classifier: Programming Language :: Python :: 3 :: Only
Classifier: Programming Language :: Python :: 3.10
Classifier: Programming Language :: Python :: 3.11
Classifier: Programming Language :: Python :: 3.12
Classifier: Programming Language :: Python :: 3.13
Classifier: Programming Language :: Python :: 3.14
Requires-Python: >=3.10
Requires-Dist: faker>=22.5
Requires-Dist: singer-sdk~=0.53.5
